aicmder/__init__.py
aicmder/common.py
aicmder/benchmark/__init__.py
aicmder/benchmark/torch_bench.py
aicmder/commands/__init__.py
aicmder/commands/extract.py
aicmder/commands/fastai.py
aicmder/commands/help.py
aicmder/commands/init.py
aicmder/commands/onnx.py
aicmder/commands/pb.py
aicmder/commands/power.py
aicmder/commands/serve.py
aicmder/commands/stop.py
aicmder/commands/utils.py
aicmder/commands/version.py
aicmder/metrics/__init__.py
aicmder/metrics/bleu/__init__.py
aicmder/metrics/bleu/bleu_scorer.py
aicmder/metrics/bleu/google_bleu.py
aicmder/metrics/bleu/nltk_bleu.py
aicmder/metrics/meteor/__init__.py
aicmder/metrics/meteor/meteor.py
aicmder/metrics/rouge/__init__.py
aicmder/metrics/rouge/rouge.py
aicmder/module/__init__.py
aicmder/module/define.py
aicmder/module/module.py
aicmder/service/LPclient.py
aicmder/service/PPpolicy.py
aicmder/service/PPqueue.py
aicmder/service/PPworker.py
aicmder/service/SPqueue.py
aicmder/service/SPworker.py
aicmder/service/Squeue.py
aicmder/service/__init__.py
aicmder/service/client.py
aicmder/service/http_service.py
aicmder/service/server.py
aicmder/service/worker.py
aicmder/torch/__init__.py
aicmder/torch/data.py
aicmder/torch/dataset.py
aicmder/torch/dist_model.py
aicmder/torch/sampler.py
aicmder/torch/train.py
aicmder/torch/transformer/__init__.py
aicmder/torch/transformer/attention.py
aicmder/torch/transformer/average_attn.py
aicmder/torch/transformer/base_model.py
aicmder/torch/transformer/decoder.py
aicmder/torch/transformer/embedding.py
aicmder/torch/transformer/encoder.py
aicmder/torch/transformer/global_attention.py
aicmder/torch/transformer/misc.py
aicmder/torch/transformer/multi_headed_attn.py
aicmder/torch/transformer/rnn_decoder.py
aicmder/torch/transformer/rnn_encoder.py
aicmder/torch/transformer/rope.py
aicmder/torch/transformer/sample_model.py
aicmder/torch/transformer/sparse_activations.py
aicmder/torch/transformer/state.py
aicmder/torch/transformer/util_class.py
aicmder/utils/__init__.py
aicmder-0.5.9.dist-info/METADATA
aicmder-0.5.9.dist-info/WHEEL
aicmder-0.5.9.dist-info/entry_points.txt
aicmder-0.5.9.dist-info/top_level.txt
aicmder-0.5.9.dist-info/RECORD
