Metadata-Version: 2.1
Name: aicmder
Version: 0.5.9
Summary: a simple ai cmder
Home-page: UNKNOWN
Author: Faith
Author-email: xianzixiang@gmail.com
License: MIT
Keywords: AI Cmder
Platform: UNKNOWN
Classifier: Development Status :: 3 - Alpha
Classifier: Intended Audience :: Developers
Classifier: Topic :: Scientific/Engineering :: Artificial Intelligence
Classifier: License :: OSI Approved :: MIT License
Classifier: Programming Language :: Python :: 3.6
Classifier: Operating System :: OS Independent
Requires-Dist: pyzmq (>=17.1.0)
Requires-Dist: GPUtil (>=1.3.0)
Requires-Dist: pickle5
Requires-Dist: packaging
Requires-Dist: termcolor
Requires-Dist: ruamel-yaml
Provides-Extra: http
Requires-Dist: falcon ; extra == 'http'
Requires-Dist: uvicorn ; extra == 'http'
Provides-Extra: nlp
Requires-Dist: torch ; extra == 'nlp'
Requires-Dist: transformers ; extra == 'nlp'
Provides-Extra: onnx
Requires-Dist: onnx ; extra == 'onnx'
Requires-Dist: onnx-tf ; extra == 'onnx'
